simply_ocr/__init__.py
simply_ocr/functions.py
simply_ocr-1.0.1.dist-info/licenses/LICENSE.md
simply_ocr-1.0.1.dist-info/METADATA
simply_ocr-1.0.1.dist-info/WHEEL
simply_ocr-1.0.1.dist-info/top_level.txt
simply_ocr-1.0.1.dist-info/RECORD
