Metadata-Version: 2.4
Name: simply-ocr
Version: 1.0.1
Summary: Read text from images
Home-page: https://github.com/jeroguzman
Author: Jeroben Guzmán
Author-email: jeroguzman@gmail.com
License: MIT
License-File: LICENSE.md
Requires-Dist: pytesseract
Requires-Dist: opencv-python
Requires-Dist: scikit-image
Requires-Dist: matplotlib
Dynamic: author
Dynamic: author-email
Dynamic: description
Dynamic: description-content-type
Dynamic: home-page
Dynamic: license
Dynamic: license-file
Dynamic: requires-dist
Dynamic: summary
